airthings_ble/__init__.py
airthings_ble/airthings_firmware.py
airthings_ble/atom/request.py
airthings_ble/atom/request_path.py
airthings_ble/atom/response.py
airthings_ble/const.py
airthings_ble/device_type.py
airthings_ble/parser.py
airthings_ble/py.typed
airthings_ble-1.1.1.dist-info/METADATA
airthings_ble-1.1.1.dist-info/WHEEL
airthings_ble-1.1.1.dist-info/licenses/LICENSE
airthings_ble-1.1.1.dist-info/RECORD
