Metadata-Version: 2.4
Name: airthings-ble
Version: 1.1.1
Summary: Manage Airthings BLE devices
License-File: LICENSE
Author: Vincent Giorgi
Requires-Python: >=3.11
Classifier: Intended Audience :: Developers
Classifier: Natural Language :: English
Classifier: Operating System :: OS Independent
Classifier: Topic :: Software Development :: Libraries
Classifier: License :: OSI Approved :: MIT License
Requires-Dist: async-interrupt (>=1.2.2)
Requires-Dist: bleak (>=1.0.1) ; python_version < "3.14"
Requires-Dist: bleak-retry-connector (>=4.4.3)
Requires-Dist: cbor2 (>=5.6.5)
Project-URL: Bug Reports, https://github.com/Airthings/airthings-ble/issues
Project-URL: Homepage, https://www.airthings.com
Project-URL: Source, https://github.com/Airthings/airthings-ble
